wagtaildocs_previews/__init__.py
wagtaildocs_previews/apps.py
wagtaildocs_previews/endpoints.py
wagtaildocs_previews/models.py
wagtaildocs_previews/serializers.py
wagtaildocs_previews/settings.py
wagtaildocs_previews/urls.py
wagtaildocs_previews/views.py
wagtaildocs_previews/migrations/0001_initial.py
wagtaildocs_previews/migrations/__init__.py
wagtaildocs_previews/tests/__init__.py
wagtaildocs_previews/tests/settings.py
wagtaildocs_previews/tests/test_models.py
wagtaildocs_previews/tests/test_views.py
wagtaildocs_previews/tests/urls.py
wagtaildocs_previews-0.0.1.dist-info/DESCRIPTION.rst
wagtaildocs_previews-0.0.1.dist-info/METADATA
wagtaildocs_previews-0.0.1.dist-info/RECORD
wagtaildocs_previews-0.0.1.dist-info/WHEEL
wagtaildocs_previews-0.0.1.dist-info/metadata.json
wagtaildocs_previews-0.0.1.dist-info/top_level.txt
