Metadata-Version: 2.0
Name: wagtaildocs-previews
Version: 0.0.1
Summary: Extend Wagtail's Documents with image previews and metadata from FilePreviews
Home-page: https://github.com/filepreviews/wagtail-filepreviews
Author: José Padilla
Author-email: jpadilla@filepreviews.io
License: MIT
Platform: UNKNOWN
Classifier: Development Status :: 4 - Beta
Classifier: Environment :: Web Environment
Classifier: Intended Audience :: Developers
Classifier: License :: OSI Approved :: MIT License
Classifier: Operating System :: OS Independent
Classifier: Programming Language :: Python
Classifier: Programming Language :: Python :: 2
Classifier: Programming Language :: Python :: 2.7
Classifier: Programming Language :: Python :: 3
Classifier: Programming Language :: Python :: 3.4
Classifier: Programming Language :: Python :: 3.5
Classifier: Framework :: Django
Classifier: Framework :: Django :: 1.8
Classifier: Framework :: Django :: 1.9
Classifier: Framework :: Django :: 1.10
Classifier: Topic :: Internet :: WWW/HTTP :: Site Management
Requires-Dist: django-model-utils (>=3.0.0,<4.0)
Requires-Dist: filepreviews (<3.0,>=2.0.2)
Requires-Dist: jsonfield (>=2.0.1<3.0)
Requires-Dist: wagtail (>=1.9,<2.0)
Provides-Extra: test
Requires-Dist: flake8 (>=3.3.0<4.0); extra == 'test'
Requires-Dist: isort (>=4.2.5,<5.0); extra == 'test'
Requires-Dist: responses (<1.0,>=0.5.1); extra == 'test'
